{"url": "https://www.philibertnet.com/fr/matagot/32360-talisman-les-terres-de-feu-3760146649118.html#img", "name": "Talisman - Les Terres de Feu", "minage": null, "duree": null, "nb_joueur": null, "description": "\nCeux qui ont forg\u00e9 la Couronne sont de retour\u00a0! De grands tr\u00e9sors et de grands dangers \u00e9mergent des profondeurs embras\u00e9es. Les Effrits sont sortis de leur royaume souterrain pour consumer tout le pays de leurs flammes mortelles. Ils ne s\u2019arr\u00eateront pas tant que tous les champs ne seront pas r\u00e9duits en cendres et que chaque habitant de la surface ne sera pas entrav\u00e9 avec des cha\u00eenes de cuivre et emmen\u00e9 dans les grottes enflamm\u00e9es des profondeurs.\nL'extension Les Terres de Feu ouvre les portes de Talisman \u00e0 une foule de dangers et, si votre p\u00e9riple dure trop longtemps, vous pourriez bien sentir les flammes vous l\u00e9cher les talons. Les Effrits, autrefois encha\u00een\u00e9s pour forger la Couronne de Commandement, se sont soulev\u00e9s pour assaillir le royaume, r\u00e9duisant tout en cendres sur leur passage.Mat\u00e9riel :81 nouvelles cartes Aventure,19 nouvelles cartes Sort,19 cartes Terrain,3 cartes Fin Alternative,4 nouveaux personnages et leurs figurines en plastique,ainsi que 34 pions Terre de Feu qui repr\u00e9sentent l\u2019\u00e9tendue de la conqu\u00eate des Effrits \u00e0 travers le pays.\n", "little_description": "Les Terres de Feu est une extension pour Talisman 4eme Edition contenant plus de 100 nouvelles cartes et 4 nouveaux personnages.", "url_image": "https://cdn2.philibertnet.com/520954-large_default/talisman-les-terres-de-feu.jpg", "prix": "26,90 \u20ac", "Theme": "", "mecanique": "", "Auteur": ""}