{"url": "https://www.philibertnet.com/fr/djeco/7449-big-pirate-3070900084230.html#img", "name": "Big Pirate", "minage": "\n\u00e0 partir de 5 ans\n", "duree": "\nmoins de 30mn\n", "nb_joueur": "\n\n2 \u00e0 4 joueur(s)\n\n", "description": "\nLes moussaillons d\u00e9barquent sur l'\u00eele de Big pirate afin de lui d\u00e9rober ses tr\u00e9sors. Mais ce dernier ne l'entend pas ainsi, bien d\u00e9cid\u00e9 \u00e0 les rattraper avant qu'ils ne reprennent la mer...\n", "little_description": "Les moussaillons d\u00e9barquent sur l'\u00eele de Big pirate afin de lui d\u00e9rober ses tr\u00e9sors.", "url_image": "https://cdn3.philibertnet.com/455809-large_default/big-pirate.jpg", "prix": "29,00 \u20ac", "Theme": "\nPirates ", "mecanique": "\nParcours ", "Auteur": "\nAlex Sanders,\u00a0Gr\u00e9gory Kirsbaum "}