{"url": "https://www.philibertnet.com/fr/helvetiq/81503-cap-sur-la-confiance-7640139532046.html#img", "name": "Cap sur la Confiance", "minage": "\n\u00e0 partir de 8 ans\n", "duree": "\n30mn \u00e0 1h\n", "nb_joueur": "\n\n2 \u00e0 8 joueur(s)\n\n", "description": "\nEt si vous d\u00e9veloppiez votre confiance en vous ?Une \u00e9norme vague se rapproche et menace le phare que vous \u00eates en train de construire. Dans Cap sur la Confiance, chaque joueur choisit un but \u00e0 atteindre ou une situation \u00e0 am\u00e9liorer, puis profite de l\u2019exp\u00e9rience des autres joueurs et met en place des strat\u00e9gies concr\u00e8tes \u00e0 appliquer dans la vraie vie. Pour gagner, vous devrez discuter entre vous, apprendre \u00e0 vous conna\u00eetre et \u00e9changer pour surmonter vos difficult\u00e9s.Ce jeu est un moyen ludique de reprendre confiance en ses capacit\u00e9s et peut \u00eatre utilis\u00e9 en classe, en famille ou entre amis. Cr\u00e9\u00e9 par deux p\u00e9dagogues suisses et inspir\u00e9 des derni\u00e8res recherches en neuroscience, il a d\u00e9j\u00e0 aid\u00e9 des centaines de personnes.Cap sur la Confiance est un jeu coop\u00e9ratif. Choisissez un but \u00e0 atteindre, r\u00e9pondez aux questions, partagez vos exp\u00e9riences avec les autres joueurs et, ensemble, d\u00e9veloppez votre confiance en vous.R\u00e9ussirez-vous \u00e0 b\u00e2tir le phare avant que la vague ne soit compl\u00e8te ?\n", "little_description": "Cap sur la Confiance est un jeu coop\u00e9ratif. Choisissez un but \u00e0 atteindre, r\u00e9pondez aux questions, partagez vos exp\u00e9riences avec les autres joueurs et, ensemble, d\u00e9veloppez votre confiance en vous.", "url_image": "https://cdn2.philibertnet.com/457561-large_default/cap-sur-la-confiance.jpg", "prix": "29,90 \u20ac", "Theme": "", "mecanique": "\nCoop\u00e9ratif ", "Auteur": "\nM\u00e9lanie Cotting & Quentin Bays "}