{"url": "https://www.philibertnet.com/fr/blam/68581-time-arena-extension-faction-scots-3770005767082.html#img", "name": "Time Arena - Extension Faction Scots", "minage": "\n\u00e0 partir de 10 ans\n", "duree": "\nmoins de 30mn\n", "nb_joueur": "\n\n2 \u00e0 4 joueur(s)\n\n", "description": "\nL\u2019ar\u00e8ne est en effervescence avec l\u2019arriv\u00e9e de nouveaux combattants !Ne regardez pas sous le kilt des \u201cScots\u201d o\u00f9 vous subirez les foudres de #balancedanstaface !\u00a0 Et aff\u00fbtez plut\u00f4t vos tactiques pour contrer leurs nouveaux pouvoirs...\u00a0\u00a0 Cette nouvelle faction de 4 nouveaux personnages \u00e9largit les strat\u00e9gies en offrant des pouvoirs in\u00e9dits! Un tronc qui provoque des d\u00e9g\u00e2ts de zone, un fant\u00f4me qui glace le sang adverse, les rejetons de Nessie qui d\u00e9barquent...\u00a0 Quoi de plus naturel pour le clan des Scots\u00a0 ?Infos compl\u00e9mentaires :Pour g\u00e9rer le temps dans Time Arena, vous avez besoin de t\u00e9l\u00e9charger l'application Time Arena avant votre premi\u00e8re partie, disponible sur les plateforme Android, IOS et Windows Phone.\n", "little_description": "La faction Scots entre dans l'ar\u00e8ne !", "url_image": "https://cdn2.philibertnet.com/415907-large_default/time-arena-extension-faction-scots.jpg", "prix": "7,90 \u20ac", "Theme": "\nFantastique ", "mecanique": "\nAffrontement ", "Auteur": "\nFabrice Lamouille "}