{"url": "https://www.philibertnet.com/fr/origames/49498-micro-mutants-usatropodes-vs-exoborg-3760243850035.html#img", "name": "Micro Mutants : Usatropodes VS Exoborg", "minage": "\n\u00e0 partir de 8 ans\n", "duree": "\nmoins de 30mn\n", "nb_joueur": "\n\n2 joueur(s)\n\n", "description": "\nLe jeu de puces avec des pouvoirs\nLa Reine des Exoborgs a entendu le cri de d\u00e9tresse des abeilles, leurs lointaines cousines, sur la plan\u00e8te Terre. L\u2019invasion est massive et soudaine et les armes humaines habituelles ne suffisent plus pour faire face \u00e0 une menace qui, bien que minuscule, menace notre plan\u00e8te enti\u00e8re\u2026\u00a0Gr\u00e2ce \u00e0 la recherche scientifique, et \u00e0 un entrainement pouss\u00e9, les Usatropodes repr\u00e9sentent la r\u00e9ponse ultime, ou presque\u2026\nA son tour, un joueur lance ses deux d\u00e9s pour savoir quels types de Soldats il peut activer. Il fait sauter ses Soldats \u00e0 l\u2019aide d\u2019un propulseur, pour recouvrir et \u00e9liminer les Soldats et les Bases adverses. D\u00e8s qu\u2019un joueur a d\u00e9truit les deux bases de son adversaire, il est d\u00e9clar\u00e9 vainqueur.\nChaque arm\u00e9e dispose de pouvoirs sp\u00e9ciaux pour des strat\u00e9gies uniques.\n", "little_description": "Micro Mutants : Usatropodes VS Exoborg est une sorte de jeu puces mais avec des pouvoirs. Le jeu m\u00e9lange deux genres, la dext\u00e9rit\u00e9 et la tactique, ce qui fonctionne \u00e0 merveille avec les plus jeunes.", "url_image": "https://cdn2.philibertnet.com/368926-large_default/micro-mutants-usatropodes-vs-exoborg.jpg", "prix": "16,50 \u20ac", "Theme": "\nFantastique ", "mecanique": "\nAffrontement,\u00a0Placement ", "Auteur": ""}