{"url": "https://www.philibertnet.com/fr/spot-games/37126-qui-veut-passer-pour-un-couillon-9782954269818.html#img", "name": "Qui Veut Passer pour un Couillon", "minage": null, "duree": "\n30mn \u00e0 1h\n", "nb_joueur": "\n\n3 \u00e0 6 joueur(s)\n\n", "description": "\nDe la politique aux stars du showbiz, \u00e0 vous de retrouver les auteurs de ce super b\u00eatisier.\u00a0Une citation dr\u00f4le (b\u00eatisier, trait d\u2019humour, phrase culte) et vous devez retrouver son auteur. Pour cela, vous pouvez faire appel \u00e0 votre \u00e9quipe avec 9 jokers au choix. Apr\u00e8s chaque joker, vous proposez une r\u00e9ponse. En cas de mauvaise r\u00e9ponse, vous prenez un autre joker etc. Apr\u00e8s avoir trouv\u00e9 la bonne r\u00e9ponse, s\u2019il vous reste des jokers, vous jouez avec une nouvelle citation. Exemples :Mourir, c'est pas facile !Oh la la ! Il a \u00e9t\u00e9 fauch\u00e9 comme un lapin en plein vol !Je ne dors pas longtemps, mais je dors viteObjectif : trouver le maximum d\u2019auteurs avec ses 9 jokers. Une partie oppose deux \u00e9quipes ou deux joueurs.Un coffret ludique pour mettre de l\u2019ambiance entre amis !Contient : un livret de 256 pages,2 s\u00e9ries de 9 jetons \u00ab Joker \u00bb,2 s\u00e9ries de 2 fiches \u00ab C\u00e9l\u00e9brit\u00e9s \u00bb.\n", "little_description": "Qui Veut Passer pour un Couillon est jeu de questions dans lequel les joueurs doivent trouver les auteurs de citations cocasses. \u00c0 vous de trouver le maximum d\u2019auteurs avec ses 9 jokers.", "url_image": "https://cdn2.philibertnet.com/344968-large_default/qui-veut-passer-pour-un-couillon.jpg", "prix": "15,00 \u20ac", "Theme": "", "mecanique": "\nCartes ", "Auteur": ""}