{"url": "https://www.philibertnet.com/fr/catch-up-games/88496-the-loop-3760273010140.html#img", "name": "The Loop", "minage": "\n\u00e0 partir de 12 ans\n", "duree": "\n1 \u00e0 2h\n", "nb_joueur": "\n\n1 \u00e0 4 joueur(s)\n\n", "description": "\nLe Docteur Foo cherche \u00e0 devenir le ma\u00eetre du monde !Pour y parvenir, il met au point une machine \u00e0 voyager dans le temps. Gr\u00e2ce \u00e0 cela, il place des clones de lui-m\u00eame \u00e0 travers le temps uniquement \u00e0 des postes essentiels, en tant que roi ou personne influente dans le pass\u00e9. \u00c0 vous, les voyageurs du temps, d\u2019emp\u00eacher le Docteur Foo de mener \u00e0 bien son plan de contr\u00f4le du monde.Collaborez avec les autres joueursThe Loop est un jeu coop\u00e9ratif qui vous oppose au mal\u00e9fique Docteur Foo. D\u00e9couvrez 4 modes de jeu diff\u00e9rents. Choisissez un personnage et \u00e9quipez-le pour faire face aux dangers qui jonchent les couloirs du temps.\u00a0\u00c0 chaque tour, le Dr Foo cr\u00e9e des clones et des failles spatio-temporelles \u00e0 l\u2019int\u00e9rieur de sa Machine temporelle pour les r\u00e9partir dans l\u2019Espace-Temps.Utilisez judicieusement vos artefacts et vos pouvoirs d'Agent Temporel pour combattre les clones. R\u00e9cup\u00e9rez de nouvelles cartes surpuissantes pour am\u00e9liorer votre Agent. En choisissant bien leur Dimension et leur effet, vous pourrez r\u00e9utiliser vos cartes plusieurs fois dans des encha\u00eenements impressionnants, gr\u00e2ce au LOOP.Faites preuve d\u2019esprit d\u2019\u00e9quipe pour \u00e9viter les Vortex et vaincre le Dr Foo avant que l\u2019Univers ne soit d\u00e9truit.\n", "little_description": "The Loop est un jeu coop\u00e9ratif qui vous oppose au mal\u00e9fique Docteur Foo. Choisissez un personnage et \u00e9quipez-le pour faire face aux dangers qui jonchent les couloirs du temps.", "url_image": "https://cdn3.philibertnet.com/476482-large_default/the-loop.jpg", "prix": "39,95 \u20ac", "Theme": "\nScience Fiction ", "mecanique": "\nCartes ", "Auteur": "\nMaxime Rambourg,\u00a0Th\u00e9o Riviere "}