{"url": "https://www.philibertnet.com/fr/cwali/107190-habitats-double-expansion-7434052043013.html#img", "name": "Habitats: Double Expansion", "minage": "\n\u00e0 partir de 14 ans\n", "duree": "\n30mn \u00e0 1h\n", "nb_joueur": "\n\n2 \u00e0 5 joueur(s)\n\n", "description": "\nCette extension de 12 tuiles contient 6 tuiles special park et 6 nouvelles tuiles objectif.Les 6 tuiles de parc DOUBLE LANDSCAPE n'apportent pas de points de victoire elles-m\u00eames, mais contiennent 2 types de paysage \u00e0 connecter \u00e0 chaque tuile adjacente. Cela permet m\u00eame de traverser des zones de type paysage, pour mieux r\u00e9pondre aux demandes de vos animaux.Les 6 tuiles d'objectifs ajoutent de la vari\u00e9t\u00e9 aux OBJECTIFS ANNUELS. Elles vous rapportent plus de points de victoire si vous battez vos adversaires en :Obtenant une bonne variation des types d'animaux.Rencontrant d'autres rangers sur le march\u00e9.Faisant plaisir \u00e0 tes visiteurs avec des tours de guet, des routes et des vues.Cr\u00e9er le lieu secret le plus myst\u00e9rieux.Construisant des endroits o\u00f9 les animaux/visiteurs peuvent se d\u00e9placer dans chaque direction.\u00catre proche d'un coin de march\u00e9.\n", "little_description": "Cette extension de 12 tuiles contient 6 tuiles special park et 6 nouvelles tuiles objectif.", "url_image": "https://cdn2.philibertnet.com/533270-large_default/habitats-double-expansion.jpg", "prix": "6,90 \u20ac", "Theme": "\nAnimaux ", "mecanique": "\nTuiles ", "Auteur": "\nCorn\u00e9 van Moorsel "}