{"url": "https://www.philibertnet.com/fr/super-meeple/110383-dice-theme-park-3770023051156.html#img", "name": "Dice Theme Park", "minage": "\n\u00e0 partir de 14 ans\n", "duree": "\n1 \u00e0 2h\n", "nb_joueur": "\n\n1 \u00e0 4 joueur(s)\n\n", "description": "\n\nSaurez-vous construire le plus beau de tous les parcs ?\n\nDans Dice Theme Park, vous incarnez un ambitieux propri\u00e9taire de parc d\u2019attractions.\n\n\u00c9tendez votre parc, am\u00e9liorez-le avec de nouveaux man\u00e8ges, et surpassez vos concurrents !\n\nIl faudra aussi recruter des employ\u00e9s, faire en sorte que votre c\u00e9l\u00e8bre mascotte divertisse les visiteurs (repr\u00e9sent\u00e9s par des d\u00e9s), et les impressionner avec de nombreuses attractions.\n\nPlus ils seront satisfaits, plus vous gagnerez d\u2019\u00e9toiles ! Attachez vos ceintures !\n\n\n", "little_description": "Dice Theme Park est un jeu de soci\u00e9t\u00e9 de manipulation de d\u00e9s, qui consiste \u00e0 cr\u00e9er et \u00e0 g\u00e9rer votre propre parc d'attractions foraines.", "url_image": "https://cdn3.philibertnet.com/542780-large_default/dice-theme-park.jpg", "prix": null, "Theme": "\nLoisirs ", "mecanique": "\nD\u00e9s ", "Auteur": "\nDaryl Andrews,\u00a0Adrian Adamescu "}