{"url": "https://www.philibertnet.com/fr/zoch-zum-spielen/13566-da-ist-der-wurm-drin-4015682321004.html#img", "name": "Da ist der Wurm Drin", "minage": "\n\u00e0 partir de 4 ans\n", "duree": "\nmoins de 30mn\n", "nb_joueur": "\n\n2 \u00e0 4 joueur(s)\n\n", "description": "\nA vos vers, pr\u00eat, partez ! Le premier rallye des vers de terre est ouvert. Faites dispara\u00eetre vos vers de terre dans la terre, encouragez-les et faites vos pronostics : quel ver de terre sera le plus rapide ? Le joueur qui d\u00e9signe le bon peut nourrir son propre ver de terre avec la p\u00e2querette et la fraise, ce qui le fait creuser encore plus vite. Le ver de terre qui sort sa t\u00eate en premier du compost, remporte la partie.\n", "little_description": "A vos vers, pr\u00eat, partez ! Le premier rallye des vers de terre est ouvert", "url_image": "https://cdn2.philibertnet.com/487354-large_default/da-ist-der-wurm-drin.jpg", "prix": "31,95 \u20ac", "Theme": "", "mecanique": "\nCourse ", "Auteur": "\n Carmen Kleinert "}