{"url": "https://www.philibertnet.com/fr/boom-boom-games/94935-objection--3770010422082.html#img", "name": "Objection !", "minage": "\n\u00e0 partir de 13 ans\n", "duree": "\n1 \u00e0 2h\n", "nb_joueur": "\n\n2 joueur(s)\n\n", "description": "\nObjection !, un jeu de cartes asym\u00e9triqueObjection ! est un jeu de cartes asym\u00e9trique pour deux joueurs qui vous propose de participer \u00e0 un proc\u00e8s dans le syst\u00e8me judiciaire am\u00e9ricain : un joueur incarnera la noble Accusation et l'autre l'in\u00e9branlable D\u00e9fense.\u00a0Tentez d'influencer le Jury pour remporter la victoire !Chaque partie commence par la phase d'Instruction, durant laquelle les joueurs choisissent des preuves essentielles pour \u00e9tayer leur affaire et enterrent les preuves qui pourraient aider leur adversaire.Vient ensuite la phase de Proc\u00e8s, au cours de laquelle les joueurs appellent des t\u00e9moins \u00e0 la barre, \u00e9laborent des arguments puissants, les confrontent aux preuves patiemment examin\u00e9es. Pour former un interrogatoire coh\u00e9rent, les joueurs devront encha\u00eener leurs cartes en faisant correspondre des symboles de Pr\u00e9jug\u00e9s.Gagnez votre proc\u00e8s !\u00a0Le joueur qui interrogera le mieux le t\u00e9moin g\u00e9n\u00e9rera le plus d'Influence qu'il pourra d\u00e9penser pour faire pencher le Jury de son cot\u00e9. Chaque jeu est diff\u00e9rent, chaque Affaire apportant des m\u00e9canismes sp\u00e9cifiques, mais le juriste avec le meilleur dossier et les arguments les plus convaincants sera s\u00fbr d'obtenir le verdict qu'il recherche !\n", "little_description": "Objection ! est un jeu de cartes asym\u00e9trique pour deux joueurs qui vous propose de participer \u00e0 un proc\u00e8s dans le syst\u00e8me judiciaire am\u00e9ricain", "url_image": "https://cdn3.philibertnet.com/496214-large_default/objection-.jpg", "prix": "26,90 \u20ac", "Theme": "\nContemporain ", "mecanique": "\nAsym\u00e9trie,\u00a0Collection,\u00a0Cartes ", "Auteur": "\nMike Gnade,\u00a0Samuel Bailey "}