{"url": "https://www.philibertnet.com/fr/cocktail-games/30254-mimtoo-famille-3760052142758.html#img", "name": "Mimtoo Famille", "minage": "\n\u00e0 partir de 6 ans\n", "duree": "\nmoins de 30mn\n", "nb_joueur": "\n\n4 \u00e0 10 joueur(s)\n\n", "description": "\nLe jeu de mimes incontournable revient en version familiale. Rassemblez toute la tribu pour un d\u00e9lire collectif \u00e0 base de mimes et de bruitages !Deux \u00e9quipes, deux pioches de cartes\u2026 et c\u2019est parti ! Votre objectif : avoir cumul\u00e9 plus de points que l\u2019\u00e9quipe adverse lorsque les deux talons seront \u00e9puis\u00e9s.\u00c0 chaque tour, vous devrez mimer des sc\u00e8nes tr\u00e8s insolites, apr\u00e8s avoir tir\u00e9 une carte dans deux pioches diff\u00e9rentes. La premi\u00e8re carte vous indiquera le sujet (par exemple \u00ab un cheval \u00bb) et la seconde, l\u2019action que ce dernier est en train d\u2019effectuer (\u00ab fume un cigare \u00bb). Si vous parvenez \u00e0 tout faire deviner \u00e0 votre \u00e9quipe avant la fin du sablier, vous marquerez les points indiqu\u00e9s sur les cartes. Sinon, il faudra retenter votre chance au prochain tour !\u2022 Le jeu d\u2019ambiance incontournable en version famille.\u2022 Des milliers de combinaisons possibles !\u2022 Des situations farfelues qui d\u00e9clencheront les rires !\u00a0\u00a0\n", "little_description": "Le jeu de mimes incontournable revient en version familiale. Rassemblez toute la tribu pour un d\u00e9lire collectif \u00e0 base de mimes et de bruitages !", "url_image": "https://cdn1.philibertnet.com/389348-large_default/mimtoo-famille.jpg", "prix": "13,50 \u20ac", "Theme": "\nHumour,\u00a0Vie quotidienne ", "mecanique": "\nAmbiance ", "Auteur": ""}