{"url": "https://www.philibertnet.com/fr/jumbo/88005-harvest-island-8410446624074.html#img", "name": "Harvest island", "minage": "\n\u00e0 partir de 8 ans\n", "duree": "\n30mn \u00e0 1h\n", "nb_joueur": "\n\n2 \u00e0 4 joueur(s)\n\n", "description": "\nQui aura la meilleure r\u00e9colte ? \nA l'intersection du Nord-est et du Sud-est de l'Asie, il existe une \u00eele unique et myst\u00e9rieuse, appel\u00e9e Formosa. Dans ce paysage magnifique, il y a des montagnes, des plaines et des collines de toutes formes et de toutes tailles, dans un environnement subtropical particuli\u00e8rement optimal pour la culture des fruits. Ces fruits sont r\u00e9colt\u00e9s \u00e0 chaque saison. Sur cette \u00eele, avec des soins appropri\u00e9s, d'extraordinaires cultures peuvent \u00eatre produites tout au long de l'ann\u00e9e.En utilisant les connaissances acquises gr\u00e2ce aux pr\u00e9visions m\u00e9t\u00e9orologiques, les joueurs doivent r\u00e9colter leurs cultures au bon moment afin de devenir le meilleur cultivateur que la terre ait jamais connu ! Contenu : \n1 Tableau des saisons 1 R\u00e8gle du jeu 12 Marqueurs de r\u00e9colte 12 Cartes champs 12 Cartes engrais 12 M\u00e9daillons d'animaux 135 Cartes\n", "little_description": "Dans Harvest Island, les joueurs jouent le r\u00f4le de cultivateurs, semant des graines dans diff\u00e9rents types de champs , selon des conditions climatiques variables, afin de maximiser leurs r\u00e9coltes.", "url_image": "https://cdn2.philibertnet.com/475178-large_default/harvest-island.jpg", "prix": "21,90 \u20ac", "Theme": "\nAnimaux ", "mecanique": "\nCartes,\u00a0Gestion,\u00a0Collection ", "Auteur": "\nChih-Fan Chen "}