{"url": "https://www.philibertnet.com/fr/repos-productions/37135-more-cash-n-more-guns-5425016923924.html#img", "name": "More Cash'n More Guns", "minage": "\n\u00e0 partir de 10 ans\n", "duree": "\nmoins de 30mn\n", "nb_joueur": "\n\n3 \u00e0 8 joueur(s)\n\n", "description": "\nDans cette extension MoreCash\u2019n More Guns, l\u2019\u00e9tau se resserre et la tension monte d\u2019un cran avec un partage du butin qui change radicalement. 16 cartes Surprise, 3 nouveaux pouvoirs et 4 nouveaux guns viennent ajouter du sel \u00e0 vos parties !\n", "little_description": "Dans cette extension MoreCash\u2019n More Guns, l\u2019\u00e9tau se resserre et la tension monte d\u2019un cran avec un partage du butin qui change radicalement. 16 cartes Surprise, 3 nouveaux pouvoirs et 4 nouveaux guns viennent ajouter du sel \u00e0 vos parties !", "url_image": "https://cdn3.philibertnet.com/344988-large_default/more-cash-n-more-guns.jpg", "prix": "17,90 \u20ac", "Theme": "\nPolar ", "mecanique": "\nAmbiance,\u00a0R\u00f4les,\u00a0Bluff ", "Auteur": "\nLudovic Maublanc "}