{"url": "https://www.philibertnet.com/fr/djeco/13269-mechanlou-3070900051263.html#img", "name": "M\u00e9chanlou", "minage": "\n\u00e0 partir de 4 ans\n", "duree": "\nmoins de 30mn\n", "nb_joueur": "\n\n2 \u00e0 4 joueur(s)\n\n", "description": "\nLes enfants auront plaisir \u00e0 jouer avec les personnages du c\u00e9l\u00e8bre conte du petit chaperon rouge. Le gagnant est le joueur qui r\u00e9unit les 6 cartes du conte. Mais attention au Loup !\n", "little_description": "Les enfants auront plaisir \u00e0 jouer avec les personnages du c\u00e9l\u00e8bre conte du petit chaperon rouge.", "url_image": "https://cdn2.philibertnet.com/455872-large_default/mechanlou.jpg", "prix": "7,90 \u20ac", "Theme": "\nContes ", "mecanique": "", "Auteur": ""}