{"url": "https://www.philibertnet.com/fr/lifestyle/101721-jouets-a-gogo-4650000323300.html#img", "name": "Jouets \u00e0 Gogo", "minage": "\n\u00e0 partir de 6 ans\n", "duree": null, "nb_joueur": "\n\n2 \u00e0 4 joueur(s)\n\n", "description": "\nImaginez-vous \u00e0 la t\u00eate de votre propre magasin de jouets !Il y en a pour tous les go\u00fbts : licornes en peluche, poup\u00e9es adorables, bou\u00e9es flamant rose, fus\u00e9es...\nPlacez vos jouets \u00e0 l\u2019endroit le plus judicieux de votre magasin pour gagner des pi\u00e8ces. Collectez des cat\u00e9gories de jouets, ou des jouets identiques, afin de r\u00e9cup\u00e9rer des r\u00e9compenses.\n", "little_description": "Jouets \u00e0 gogo est un jeu de strat\u00e9gie facile avec des r\u00e8gles simples. Les joueurs y incarnent des g\u00e9rants de magasins de jouets qui devront organiser leur magasin pour r\u00e9ussir \u00e0 vendre le plus de jouets possibles.", "url_image": "https://cdn2.philibertnet.com/516941-large_default/jouets-a-gogo.jpg", "prix": "15,90 \u20ac", "Theme": "\nLoisirs ", "mecanique": "\nTuiles,\u00a0Combinaison ", "Auteur": "\nEvgeny Niitin "}