{"url": "https://www.philibertnet.com/fr/matagot/35666-talisman-le-royaume-sylvestre-3760146649132.html#img", "name": "Talisman - Le Royaume Sylvestre", "minage": "\n\u00e0 partir de 14 ans\n", "duree": null, "nb_joueur": null, "description": "\nLa Brume se dissipe et des Arbres Ancestraux apparaissent\u2026Pour la premi\u00e8re fois depuis des si\u00e8cles, le mythique Royaume Sylvestre est de retour dans le monde des mortels. Parmi les arbres magistraux et le long des chemins sinueux, on peut trouver des richesses et des pouvoirs au-del\u00e0 de l'imagination. Mais il rec\u00e8le aussi de grands dangers. Le Roi Ob\u00e9ron et la Reine Titania, des \u00eatres sans \u00e2ge faits de destin et de magie, ne prendront pas l'invasion de leur royaume \u00e0 la l\u00e9g\u00e8re. Choisirez-vous un camp dans la lutte entre les deux monarques des f\u00e9es, ou irez-vous de lavant pour vous-m\u00eame\u2026\u2026 et choisirez-vous votre propre Voie?Talisman : Le Royaume Sylvestre propose une nouvelle R\u00e9gion que les h\u00e9ros aventureux vont pouvoir explorer. Un nouveau plateau ajust\u00e9 et plus de 100 nouvelles cartes donnent vie \u00e0 ce e for\u00eat magique bouillonnante de vie. Cinq nouveaux personnages, tous repr\u00e9sent\u00e9s par une gurine d\u00e9taill\u00e9e, proposent une nouvelle exp\u00e9rience de jeu fantastique.Aventurez-vous dans les profondeurs de la for\u00eat, braves voyageurs, et d\u00e9couvrez vos Destin\u00e9es au coeur du Royaume Sylvestre!Contenu1 Livret de R\u00e8gles1 Plateau Royaume Sylvestre103 Cartes Royaume Sylvestre10 cartes Aventure20 Cartes Voie14 Cartes Destin\u00e9e5 Cartes Sort3 Cartes Fin Alternative5 Cartes Personnage22 Pions Personnage5 Figurines en Plastique.\n", "little_description": "Une nouvelle R\u00e9gion : Le Royaume Sylvestre \u00e0 explorer dans Talisman 4e Edition. Vous trouverez dans cette extension un nouveau plateau ajust\u00e9 et plus de 100 nouvelles cartes ainsi que 5 nouveaux personnages.", "url_image": "https://cdn1.philibertnet.com/520495-large_default/talisman-le-royaume-sylvestre.jpg", "prix": "44,90 \u20ac", "Theme": "", "mecanique": "", "Auteur": ""}