{"url": "https://www.philibertnet.com/fr/studio-h/108183-suspects-2-3616450015012.html#img", "name": "Suspects 2", "minage": "\n\u00e0 partir de 10 ans\n", "duree": "\n1 \u00e0 2h\n", "nb_joueur": "\n\n1 \u00e0 6 joueur(s)\n\n", "description": "\nDans cette seconde boite de Suspects, retrouvez l'intr\u00e9pide et brillante Claire Harper \u00e0 diff\u00e9rents moments de sa vie... mais toujours poursuivie par le myst\u00e8re.En 1921 alors qu\u2019elle fr\u00e9quente les bancs de son \u00e9cole \u00e0 Nottingham dans \u00abLes larmes de Shakespeare\u00bb.En 1948, lors du premier grand \u00e9v\u00e8nement d\u2019apr\u00e8s-guerre : les Jeux Olympiques de Londres dans \u00ab Mort \u00e0 l\u2019arriv\u00e9e \u00bb.En 1971, dans \u00abLe Myst\u00e8re de la dame du lac\u00bb alors que Claire go\u00fbte au calme de la Suisse pour \u00e9crire ses\nm\u00e9moires... Principe du jeu Suspects est une s\u00e9rie de jeu d\u2019enqu\u00eates et de r\u00e9flexion avec des r\u00e8gles minimales, et centr\u00e9e sur les personnages \u00e0 la mani\u00e8re des romans d\u2019Agatha Christie. Chaque bo\u00eete est ax\u00e9e sur un enqu\u00eateur et une \u00e9poque, et propose 3 sc\u00e9narios avec des personnages bien travaill\u00e9s et des intrigues solides.\n", "little_description": "Suspects 2 marque le retour de l\u2019h\u00e9ro\u00efne Claire Harper apr\u00e8s le succ\u00e8s du personnage et de ses premi\u00e8res aventures dans 3 sc\u00e9narios aux ambiances tr\u00e8s diff\u00e9rentes mais li\u00e9s entre eux par des personnages r\u00e9currents.", "url_image": "https://cdn3.philibertnet.com/536358-large_default/suspects-2.jpg", "prix": "26,90 \u20ac", "Theme": "\nEnqu\u00eate ", "mecanique": "\nD\u00e9duction,\u00a0Coop\u00e9ratif ", "Auteur": "\nGuillaume Montiage,\u00a0Manuel Rozoy "}