{"url": "https://www.philibertnet.com/fr/ravensburger/88423-labyrinth-harry-potter-4005556260317.html#img", "name": "Labyrinth - Harry Potter", "minage": "\n\u00e0 partir de 7 ans\n", "duree": "\nmoins de 30mn\n", "nb_joueur": "\n\n2 \u00e0 4 joueur(s)\n\n", "description": "\nExplorez le plus magique des labyrinthes \u00e0 la recherche des personnages de la saga Harry Potter. \nQui r\u00e9ussira le mieux \u00e0 s'orienter \u00e0 travers ce labyrinthe Harry Potter et trouvera les chemins menant aux c\u00e9l\u00e8bres pensionnaires de Poudlard ?\nHarry, Ron, Hermione, mais \u00e9galement le professeur Dumbledore, Hagrid ou encore Edwige, la chouette de Harry attendent que vous les retrouviez. \u00c0 vous de faire coulisser habilement les plaques du labyrinthe pour transformer les impasses en passages .Vous pourrez ainsi cr\u00e9er de nouveaux chemins et atteindre les personnages recherch\u00e9s. Le c\u00e9l\u00e8bre labyrinthe en mouvement. Des r\u00e8gles simples, et des parties toujours palpitantes !\n", "little_description": "Entrez dans le monde magique d'Harry Potter gr\u00e2ce au jeu classique Labyrinthe ! Tentez de vous frayer un chemin pour retrouver les pensionnaires de Poudlard.", "url_image": "https://cdn3.philibertnet.com/476319-large_default/labyrinth-harry-potter.jpg", "prix": "34,00 \u20ac", "Theme": "\nMagie ", "mecanique": "\nTuiles ", "Auteur": "\nMax J. Kobbert "}