{"url": "https://www.philibertnet.com/fr/iello/47997-smash-up-vf-vous-l-aurez-voulu-3760175513510.html#img", "name": "Smash Up - Vous l'Aurez Voulu", "minage": "\n\u00e0 partir de 12 ans\n", "duree": "\n30mn \u00e0 1h\n", "nb_joueur": "\n\n2 \u00e0 4 joueur(s)\n\n", "description": "\nEt vous avez imagin\u00e9 l'une des toutes meilleures extensions jamais cr\u00e9\u00e9es !Nous vous avons laiss\u00e9 voter et d\u00e9terminer quelles nouvelles factions vous souhaitiez voir d\u00e9barquer dans Smash Up, et il faut reconna\u00eetre que vous avez \u00e9t\u00e9 plut\u00f4t g\u00e9niaux. Les quatre factions pr\u00e9sentes dans cette bo\u00eete sont arriv\u00e9es en t\u00eate devant des milliers de candidatures, puis elles ont surv\u00e9cu \u00e0 un vote de soutien, avant d\u2019arriver, aujourd'hui, entre vos mains !Smash Up: Vous l'aurez voulu ! contient des Requins, qui ont bien l'intention de m\u00e2chouiller leurs adversaires. Il y a aussi les Superh\u00e9ros, volant hors des pages de leurs comics pour an\u00e9antir leurs ennemis. Vous avez \u00e9galement choisi de voir les L\u00e9gendes de la Mythologie Grecque envahir votre table, impassibles devant la puissance et la force destructrice des Dragons !M\u00eame si Smash Up : Vous l\u2019aurez voulu ! est une extension du jeu Smash Up, le jeu de base n\u2019est pas indispensable : les 5 Factions propos\u00e9es ici vous suffiront pour jouer des parties \u00e0 2 joueurs !\n", "little_description": "Smash Up : Vous l\u2019aurez voulu ! est une extension du jeu Smash Up qui ne n\u00e9cessite pas forc\u00e9ment le jeu de base. Retrouvez les nouvelles factions : les Requins, les Superh\u00e9ros, les L\u00e9gendes de la Mythologie Grecque et les Dragons.", "url_image": "https://cdn2.philibertnet.com/366045-large_default/smash-up-vf-vous-l-aurez-voulu.jpg", "prix": "15,00 \u20ac", "Theme": "", "mecanique": "\nCartes,\u00a0Affrontement ", "Auteur": "\nPaul Peterson "}