{"url": "https://www.philibertnet.com/fr/lansay/109377-fort-boyard-le-jeu-de-cartes-3181860751220.html#img", "name": "Fort Boyard - Le Jeu de Cartes", "minage": "\n\u00e0 partir de 7 ans\n", "duree": "\nmoins de 30mn\n", "nb_joueur": "\n\n2 \u00e0 6 joueur(s)\n\n", "description": "\nEn individuel ou en \u00e9quipe, part \u00e0 la conqu\u00eate du Fort !Retrouve l\u2019exp\u00e9rience du jeu de soci\u00e9t\u00e9 Fort Boyard dans un format voyage ! De nouvelles \u00e9preuves t\u2019attendent. R\u00e9ponds correctement aux \u00e9nigmes du P\u00e8re Fouras et r\u00e9ussis les \u00e9preuves pour gagner des cl\u00e9s et des indices afin d\u2019acc\u00e9der \u00e0 la salle du tr\u00e9sor. Donne le bon MOT CODE pour remporter tous les Boyards.\nDe nouvelles cartes (SWITCH et BONUS) t\u2019aideront dans ta course. Mais attention \u00e0 ne pas tomber sur la carte PRISON si tu ne veux pas passer ton tour !\u00a0\n", "little_description": "Retrouve l\u2019exp\u00e9rience du jeu de soci\u00e9t\u00e9 Fort Boyard dans un format voyage !", "url_image": "https://cdn1.philibertnet.com/539904-large_default/fort-boyard-le-jeu-de-cartes.jpg", "prix": "14,50 \u20ac", "Theme": "", "mecanique": "\nCartes ", "Auteur": ""}