{"url": "https://www.philibertnet.com/fr/zman-games/10544-carcassonne-vf-3558380096337.html#img", "name": "Carcassonne", "minage": "\n\u00e0 partir de 8 ans\n", "duree": "\n30mn \u00e0 1h\n", "nb_joueur": "\n\n2 \u00e0 5 joueur(s)\n\n", "description": "\nCarcassonne, un jeu \u00e0 l\u2019atmosph\u00e8re m\u00e9di\u00e9vale\nReplongez dans l\u2019ambiance du Moyen-\u00c2ge du Sud de la France en partant \u00e0 l\u2019assaut de ses terres, chemins et villes. D\u00e9veloppez la meilleure strat\u00e9gie pour affirmer votre pouvoir. D\u00e9jouez les plans de vos adversaires et triomphez en contr\u00f4lant le plus de territoires.\nCarcassonne, un jeu accessible et strat\u00e9gique\nD\u2019une dur\u00e9e comprise entre 30 minutes et 1h, Carcassonne s\u2019appuie sur la m\u00e9canique des dominos. Une partie se d\u00e9roule autour d\u2019un plateau sur lequel chaque joueur pose des tuiles repr\u00e9sentant par exemple des villages, des \u00e9glises, des routes ou des champs. Construisez un paysage et placez vos pions en suivant votre strat\u00e9gie. Vous obtiendrez des points en fonction de la longueur des routes, de la grandeur des bourgs ou des champs que vous contr\u00f4lerez.\nLorsque toutes les tuiles ont \u00e9t\u00e9 jou\u00e9es, le jeu est termin\u00e9. Le paysage ainsi constitu\u00e9 reste fig\u00e9 et le d\u00e9compte des points peut s\u2019effectuer.\nLe joueur avec le plus grand nombre de points remporte la partie.\n", "little_description": "Retournez \u00e0 l\u2019\u00e9poque m\u00e9di\u00e9vale avec Carcassonne. Construisez un paysage \u00e0 l\u2019aide de tuiles, puis tentez de contr\u00f4ler un maximum de territoires. un jeu o\u00f9 la strat\u00e9gie s'allie \u00e0 la simplicit\u00e9.", "url_image": "https://cdn2.philibertnet.com/542823-large_default/carcassonne-vf.jpg", "prix": "31,50 \u20ac", "Theme": "\nMoyen Age ", "mecanique": "\nConnexion,\u00a0Placement,\u00a0Majorit\u00e9,\u00a0Tuiles ", "Auteur": "\nKlaus-J\u00fcrgen Wrede "}