{"url": "https://www.philibertnet.com/fr/game-brewer/81268-fuji-koro-5407004490755.html#img", "name": "Fuji Koro", "minage": "\n\u00e0 partir de 12 ans\n", "duree": "\n1 \u00e0 2h\n", "nb_joueur": "\n\n1 \u00e0 6 joueur(s)\n\n", "description": "\nJapon H\u014dsei 4 (1707).Le mont Fuji est sur le point d'entrer en \u00e9ruption. La lave rouge et chaude consommera bient\u00f4t les trois Seien-ji secrets (\u8056\u7159\u5bfa), temples sacr\u00e9s cach\u00e9s profond\u00e9ment dans les entrailles du volcan. Le Sh\u014dgun est d\u00e9termin\u00e9 \u00e0 pr\u00e9server le pr\u00e9cieux patrimoine et envoie ses guerriers samoura\u00efs les plus nobles et les plus dou\u00e9s \u00e0 l'int\u00e9rieur du volcan pour en r\u00e9cup\u00e9rer les biens pr\u00e9cieux.Apr\u00e8s une mont\u00e9e ext\u00e9nuante \u00e0 travers des temp\u00eates de neige et un terrain rocheux tra\u00eetre, les samoura\u00efs trouvent l'entr\u00e9e qui m\u00e8ne \u00e0 la caverne.Le volcan gronde et les murs se mettent \u00e0 trembler ! Le sol sous leurs pieds s'effondre et nos courageux samoura\u00efs tombent dans l'immense caverne qui contient les trois temples, qui s'enfoncent lentement dans la lave qui couve.C'est maintenant \u00e0 nos h\u00e9ros d'explorer la caverne et de trouver autant de reliques, de manuscrits sacr\u00e9s et de moines que possible, pour les ramener sains et saufs au Shogun avant l'\u00e9ruption du volcan et que tout soit perdu \u00e0 jamais.Fuji Koro peut \u00eatre jou\u00e9 en mode comp\u00e9titif avec 2 \u00e0 6 joueurs ou en mode coop\u00e9ratif avec 1 \u00e0 6 joueurs.Les joueurs vont essayer de rassembler des parchemins sacr\u00e9s et des plans pour des armes magiques, rassembler des ressources, fabriquer le meilleur \u00e9quipement possible, et essayer de sortir du volcan avant qu'il n'explose compl\u00e8tement. Pour empirer les choses, les joueurs rencontreront des dragons fantastiques au cours de leur voyage \u00e0 travers le volcan, qu'ils devront essayer de vaincre par eux-m\u00eames ou avec l'aide d'autres joueurs.La partie se poursuit jusqu'\u00e0 la phase finale de la partie, qui est d\u00e9clench\u00e9e lorsqu'un joueur atteint 30 points de victoire. Une fois que cela se produit, les joueurs auront 8 derniers tours pour s'\u00e9chapper du volcan.Pour gagner le jeu, un joueur devra marquer le plus de points de victoire en battant des dragons, en explorant la grotte, en fabriquant les bonnes armes et en amenant du mat\u00e9riel magique, des dents de dragon et des moines au Sh\u014dgun pendant la phase finale du jeu.\n", "little_description": "Le mont Fuji est sur le point d'entrer en \u00e9ruption. Le Sh\u014dgun est d\u00e9termin\u00e9 \u00e0 pr\u00e9server le pr\u00e9cieux patrimoine et envoie ses guerriers samoura\u00efs les plus nobles et les plus dou\u00e9s \u00e0 l'int\u00e9rieur du volcan pour en r\u00e9cup\u00e9rer les biens pr\u00e9cieux.", "url_image": "https://cdn2.philibertnet.com/457003-large_default/fuji-koro.jpg", "prix": "72,95 \u20ac", "Theme": "\nAsie ", "mecanique": "\nCoop\u00e9ratif,\u00a0Tuiles,\u00a0Actions,\u00a0D\u00e9s,\u00a0Stop ou encore ", "Auteur": "\nJerome Demeyere "}