{"url": "https://www.philibertnet.com/fr/libellud/13680-dixit-odyssey-3558380024811.html#img", "name": "Dixit Odyssey", "minage": "\n\u00e0 partir de 8 ans\n", "duree": "\n30mn \u00e0 1h\n", "nb_joueur": "\n\n3 \u00e0 Plus de 10 joueurs\n\n", "description": "\nReplongez dans l\u2019univers fantastique de Dixit\u00a0!Dixit Odyssey, \u00e9dit\u00e9 par Libellud, est la 2e extension du c\u00e9l\u00e8bre Dixit, le jeu multi-prim\u00e9 \u00e0 travers le monde. Avec ce nouvel opus, \u00a0laissez voguer votre imagination et partez \u00e0 la conqu\u00eate de nouveaux mondes oniriques et enchanteurs\u00a0!Dixit Odyssey se pr\u00e9sente sous la forme d\u2019un stand alone. Il peut donc se jouer ind\u00e9pendamment de Dixit ou Dixit 2.Dixit Odyssey est jouable de 3 \u00e0 12 joueurs, \u00e0 partir de 8 ans.Ce nouveau Dixit am\u00e8ne avec lui son lot de nouveaut\u00e9s. Il propose 84 nouvelles cartes emmenant le joueur \u00e0 la d\u00e9couverte de mondes \u00e9tranges peupl\u00e9s par de myst\u00e9rieux habitants. Pour marquer et illustrer ce nouvel univers, Pierre Lechevalier (dit Pi\u00e9r\u00f4) a r\u00e9alis\u00e9 les dessins des cartes tandis que Marie Cardouat (illustratrice de Dixit et Dixit 2) s\u2019est occup\u00e9e de la colorisation de ces derni\u00e8res.En outre, Dixit Odyssey offre un mat\u00e9riel de jeu adapt\u00e9 pour jouer \u00e0 Dixit jusqu\u2019\u00e0 12 joueurs\u00a0: nouveau plateau de jeu pliable, \u00a0tablettes de vote et pions-lapins plus stables.Dixit Odyssey introduit, pour les joueurs qui le souhaitent, de nouvelles fa\u00e7ons de jouer \u00e0 Dixit \u00e0 plus de 6 joueurs, en plus des r\u00e8gles \u00ab\u00a0classiques\u00a0\u00bb.Enfin la bo\u00eete de Dixit Odyssey permet aux possesseurs de Dixit et Dixit 2 de ranger l\u2019int\u00e9gralit\u00e9 de leurs cartes dans un seul et unique jeu.\n", "little_description": "Avec Dixit Odyssey, la 2e extension de Dixit, replongez dans l\u2019univers fantastique du plus onirique des jeux. Dans ce nouvel opus, laissez voguer votre imagination et partez \u00e0 la conqu\u00eate de nouveaux mondes enchanteurs.", "url_image": "https://cdn2.philibertnet.com/312353-large_default/dixit-odyssey.jpg", "prix": "26,90 \u20ac", "Theme": "\nVie quotidienne,\u00a0Onirique ", "mecanique": "\nD\u00e9duction,\u00a0Cr\u00e9ativit\u00e9 ", "Auteur": "\nJ.L. Roubira "}