{"url": "https://www.philibertnet.com/fr/keyforge-fr/69419-keyforge-l-appel-des-archontes-8435407622838.html#img", "name": "Keyforge - L'Appel des Archontes", "minage": "\n\u00e0 partir de 14 ans\n", "duree": "\n30mn \u00e0 1h\n", "nb_joueur": "\n\n2 joueur(s)\n\n", "description": "\nEntrez dans un monde o\u00f9 tout est possible avec KeyForge ! Ici, dans ce jeu de deck unique, une premi\u00e8re mondiale, deux joueurs deviennent des archontes en train de forger des cl\u00e9s qui d\u00e9verrouillent les vo\u00fbtes cach\u00e9es du creuset, un monde artificiel construit \u00e0 partir de morceaux d'innombrables plan\u00e8tes. Avec un incroyable \u00e9ventail de cr\u00e9atures, d'artefacts et de capacit\u00e9s, il n'existe pas deux jeux de cartes identiques et deux parties ne seront jamais les m\u00eames !Jouer avec le set de d\u00e9part de KeyForge n'est que le d\u00e9but de vos aventures. Vous pouvez \u00e9tendre votre arsenal avec les decks, qui offrent chacun une exp\u00e9rience de jeu compl\u00e8te sans avoir besoin de construire un deck ou des boosters suppl\u00e9mentaires. Chaque deck est compl\u00e8tement unique en son genre et ne peut pas \u00eatre modifi\u00e9, ce qui vous demandera d'utiliser toutes les factions de votre deck pour remporter la victoire. Chaque deck porte un nom distinct et est constitu\u00e9 d'un m\u00e9lange unique de cartes, de tactiques, et de potentiel strat\u00e9gique. Dans chaque pack, vous aurez l'opportunit\u00e9 de devenir le meilleur au monde en jouant vos decks. Vos \u00e9quipes auront-elles la force, les comp\u00e9tences et la ruse n\u00e9cessaires pour gagner ?\n", "little_description": "Prenez les r\u00eanes d\u2019un deck Archonte !", "url_image": "https://cdn1.philibertnet.com/418182-large_default/keyforge-l-appel-des-archontes.jpg", "prix": "8,90 \u20ac", "Theme": "\nFantastique,\u00a0Science Fiction ", "mecanique": "\nCartes,\u00a0Pouvoirs ", "Auteur": "\n Richard Garfield  "}