{"url": "https://www.philibertnet.com/fr/piatnik/109276-turtle-bay-9001890665066.html#img", "name": "Turtle Bay", "minage": "\n\u00e0 partir de 6 ans\n", "duree": "\nmoins de 30mn\n", "nb_joueur": "\n\n2 \u00e0 4 joueur(s)\n\n", "description": "\nBut du jeu: Amener le premier toutes ses tortues \u00e0 l'oc\u00e9an.\nM\u00e9canique : Une fois que les petites tortues de mer sont\nsur le sable, personne ne peut les arr\u00eater. Elles foncent vers l\u0092oc\u00e9an.\nMais avec toute cette agitation, il arrive qu\u0092une tortue soit heurt\u00e9e\npar une autre et qu\u0092elle se retrouve sur le dos. Elle devra alors\nattendre patiemment jusqu\u0092\u00e0 ce qu\u0092une autre tortue lui vienne en aide et\nla retourne \u00e0 nouveau. \nLa r\u00e8gle en bref :\nToutes les tortues sont sur la plage au d\u00e9part.\nChaque joueur choisit une couleur et place ses tortues en file indienne.\nA ton tour de jeu, tu pourras lancer le ou les d\u00e9s et avancer une tortue\nde ta couleur. Choisis la tortue de ton choix, pose le marqueur de\nposition \u00e0 c\u00f4t\u00e9 d'elle et avance ta tortue selon le score du d\u00e9 le plus\n\u00e9lev\u00e9.\nTu devras ensuite retourner toutes les tortues que tu as d\u00e9pass\u00e9, y\ncompris les tiennes.\nC'est ensuite au tour du joueur suivant. Mais attention, seules les tortues sur le ventre peuvent avancer.\nSelon le nombre de tes tortues sur le dos, tu lanceras 1, 2 ou 3 d\u00e9s. \nChoisis bien la tortue qui va avancer et planifie les retournements pour \u00eatre le premier \u00e0 mener toutes tes tortues \u00e0 l'oc\u00e9an !\n", "little_description": "Turtle Bay est un jeu de course familial, dans lequel vous devrez \u00eatre le premier \u00e0 faire parvenir vos tortues jusqu'\u00e0 l'oc\u00e9an .", "url_image": "https://cdn1.philibertnet.com/539635-large_default/turtle-bay.jpg", "prix": "22,90 \u20ac", "Theme": "\nAnimaux ", "mecanique": "\nCourse ", "Auteur": "\nWolfgang Riedl "}