{"url": "https://www.philibertnet.com/fr/iello/87009-for-sale-3760175517044.html#img", "name": "For Sale", "minage": "\n\u00e0 partir de 10 ans\n", "duree": "\n30mn \u00e0 1h\n", "nb_joueur": "\n\n3 \u00e0 6 joueur(s)\n\n", "description": "\nLes agents immobiliers sont des requins ? Prouvez que vous \u00eates le meilleur !For Sale, c\u2019est un jeu d\u2019ench\u00e8res accessible et malin ! Achetez des maisons au plus bas prix\u2026 et revendez-les en faisant d'\u00e9normes profits ! Saurez-vous estimer au mieux la valeur des biens pour remporter les plus gros ch\u00e8ques ?V\u00e9ritable r\u00e9f\u00e9rence du jeu d\u2019ench\u00e8res ouvertes et ferm\u00e9es, For Sale mixe l\u2019efficacit\u00e9 des classiques du genre \u00e0 la subtilit\u00e9 de m\u00e9canismes originaux. Simple, f\u00fbt\u00e9 et jubilatoire !\n", "little_description": "For Sale, c\u2019est un jeu d\u2019ench\u00e8res accessible et malin ! Achetez des maisons au plus bas prix\u2026 et revendez-les en faisant d'\u00e9normes profits ! Saurez-vous estimer au mieux la valeur des biens pour remporter les plus gros ch\u00e8ques ?", "url_image": "https://cdn2.philibertnet.com/472323-large_default/for-sale.jpg", "prix": "14,00 \u20ac", "Theme": "", "mecanique": "\nEnch\u00e8res ", "Auteur": "\nStefan Dorra "}