{"url": "https://www.philibertnet.com/fr/gigamic/24977-bazar-bizarre-20-3421272106028.html#img", "name": "Bazar Bizarre 2.0", "minage": "\n\u00e0 partir de 6 ans\n", "duree": "\n30mn \u00e0 1h\n", "nb_joueur": "\n\n2 \u00e0 8 joueur(s)\n\n", "description": "\nUne fant\u00f4messe arrive au ch\u00e2teau avec de nouveaux objets et elle est bien d\u00e9cid\u00e9e \u00e0 mettre encore plus le bazar !La r\u00e8gle de base est la m\u00eame que celle de Bazar Bizarre :Cinq figurines d\u2019une certaine couleur sont dispos\u00e9es devant vous. Puis, une carte Objet est retourn\u00e9e. Si un des objets y figure \u00e0 l\u2019identique, saisissez-vite la figurine correspondante ! Sinon, attrapez la seule qui n\u2019a rien en commun avec la carte : ni forme, ni couleur.Mais attention, car des variantes diaboliques viennent tout chambouler\u2026Pour les plus t\u00e9m\u00e9raires, d\u00e9couvrez la r\u00e8gle qui vous permet de combiner Bazar Bizarre et Bazar Bizarre 2.0 : un v\u00e9ritable d\u00e9fi !\n", "little_description": "Une fant\u00f4messe arrive au ch\u00e2teau avec de nouveaux objets et elle est bien d\u00e9cid\u00e9e \u00e0 mettre encore plus le bazar !", "url_image": "https://cdn1.philibertnet.com/325692-large_default/bazar-bizarre-20.jpg", "prix": "16,90 \u20ac", "Theme": "", "mecanique": "\nR\u00e9flexes ", "Auteur": "\nJacques Zeimet "}