{"url": "https://www.philibertnet.com/fr/steve-jackson-games/103999-munchkin-9-jurassique-farce-8435407634473.html#img", "name": "Munchkin 9 : Jurassique Farce", "minage": "\n\u00e0 partir de 10 ans\n", "duree": "\n1 \u00e0 2h\n", "nb_joueur": "\n\n3 \u00e0 6 joueur(s)\n\n", "description": "\nLes aventuriers claustrophobes n'auront pas envie de s\u2019enfoncer sous terre pour \u00ab\u2009pexer\u2009\u00bb et accumuler des tr\u00e9sors\u2009!Nous avons la solution. Pourquoi ne pas affronter les monstres les plus terribles de la pr\u00e9histoire. Nul besoin d\u2019un ast\u00e9ro\u00efde pour provoquer l\u2019extinction des dinosaures quand il y a des Munchkins avides de niveaux dans les parages\u2009!\nCe suppl\u00e9ment se focalise sur deux types de cartes en particulier : les Fid\u00e8les serviteurs et les Montures (introduites dans Munchkin 4). Le tout, bien s\u00fbr, aux couleurs des dinosaures\u2009!Les Fid\u00e8les serviteurs et autres acolytes sont trait\u00e9s de la m\u00eame mani\u00e8re en termes de r\u00e8gles. Dans ce suppl\u00e9ment, ce sont des cartes Porte. Vous pouvez jouer un Fid\u00e8le serviteur \u00e0 n\u2019importe quel moment, m\u00eame en combat, tant que vous n\u2019en avez qu\u2019un \u00e0 la fois. Si vous perdez un combat, au lieu de lancer un d\u00e9 pour D\u00e9guerpir, vous pouvez d\u00e9fausser un Fid\u00e8le serviteur et tout ce qu\u2019il porte\u2009! C\u2019est beau, un tel sacrifice, \u00e7a met les larmes aux yeux, m\u00eame s\u2019il a fallu un peu le pousser dans le dos.Une carte Tricheur\u2009! peut m\u00eame \u00eatre utilis\u00e9e pour b\u00e9n\u00e9ficier d\u2019un Fid\u00e8le serviteur suppl\u00e9mentaire, ou pour permettre \u00e0 un Fid\u00e8le serviteur de porter un objet qui lui serait normalement interdit.Parce qu\u2019elle file des super bonus, la Monture est un \u00e9l\u00e9ment essentiel. Les nouvelles Montures (Bronto de Selle, Pt\u00e9ro de Seller, Gigantosaure de Selle, Tric\u00e9ratops de Selle, Raptor de Selle, etc.) se trouvent dans le paquet Porte. Comme pour les Fid\u00e8les serviteurs, aucun joueur ne peut avoir plus d\u2019une Monture sauf en utilisant une carte Tricheur\u2009! La mention \u00ab\u2009Gros\u2009\u00bb sur les cartes Monture n\u2019est l\u00e0 que pour d\u00e9terminer quels Pi\u00e8ges et Mal\u00e9dictions peuvent les affecter et pour emp\u00eacher les Voleurs de venir vous les piquer discr\u00e8tement. Mais si une Monture pioch\u00e9e ne vous int\u00e9resse pas, tapez dessus\u2009! Choisissez de la consid\u00e9rer comme un monstre. En ce cas, le Niveau du monstre est consid\u00e9r\u00e9 comme \u00e9tant le double du bonus de combat indiqu\u00e9 en haut de la carte, et le fait de le vaincre rapporte un Tr\u00e9sor et un Niveau.\n", "little_description": "Affrontez des Porc-\u00c9pic Jurassique, des Choristosaurus, un Fossile Hostile, un Rhinosaure, et plein d\u2019autres monstres d\u00e9lirants\u2009!", "url_image": "https://cdn2.philibertnet.com/523773-large_default/munchkin-9-jurassique-farce.jpg", "prix": "14,95 \u20ac", "Theme": "\nM\u00e9di\u00e9val,\u00a0Fantastique ", "mecanique": "\nCartes,\u00a0Ambiance ", "Auteur": ""}