{"url": "https://www.philibertnet.com/fr/smart-games/44958-trois-petits-cochons-deluxe-5414301518853.html#img", "name": "Trois Petits Cochons Deluxe", "minage": "\n\u00e0 partir de 3 ans\n", "duree": "\nmoins de 30mn\n", "nb_joueur": "\n\n1 joueur(s)\n\n", "description": "\nIl \u00e9tait une fois\u2026Placerez-vous correctement les maisons afin qu\u2019ils puissent jouer \u00e0 l\u2019ext\u00e9rieur ? Et si jamais le loup appara\u00eet, saurez-vous les aider en les prot\u00e9geant \u00e0 l\u2019int\u00e9rieur des maisons ?\n\u00ab Les Trois Petits Cochons \u00bb est un jeu de r\u00e9flexion id\u00e9al pour les jeunes enfants. Vous y trouverez 3 grosses pi\u00e8ces de jeu juch\u00e9es de maisons ainsi que 4 figurines (les cochons et le loup) faciles \u00e0 manipuler.\nLes enfants adoreront voir les cochons regarder \u00e0 travers les fen\u00eatres de leur maison. Vous trouverez \u00e9galement un livre de conte illustr\u00e9 ainsi qu\u2019un livret de 48 d\u00e9fis.\n", "little_description": "Les Trois Petits Cochons est un jeu de r\u00e9flexion pour enfants dans lequel les joueurs doivent placer les maisons pour que les cochons jouent \u00e0 l'ext\u00e9rieur ou se prot\u00e8gent du loup selon la situation.", "url_image": "https://cdn3.philibertnet.com/501403-large_default/trois-petits-cochons-deluxe.jpg", "prix": "24,99 \u20ac", "Theme": "\nAnimaux ", "mecanique": "\nCasse-t\u00eate ", "Auteur": ""}