{"url": "https://www.philibertnet.com/fr/ludi-concept/83818-cuistot-fury-3770009650021.html#img", "name": "Cuistot Fury", "minage": "\n\u00e0 partir de 7 ans\n", "duree": "\nmoins de 30mn\n", "nb_joueur": "\n\n2 \u00e0 9 joueur(s)\n\n", "description": "\nRejoignez une brigade de cuistots et d\u00e9fiez vos concurrents dans des duels gastronomiques \u00e0 couteaux tir\u00e9s !Cuistot Fury est un jeu de comp\u00e9tition en \u00e9quipes pour 2 \u00e0 9 joueurs r\u00e9partis dans 2 \u00e0 3 brigades de cuistots. Leur but : pr\u00e9parer les meilleures recettes et servir tous leurs clients, dans un contre-la-montre acharn\u00e9 o\u00f9 chaque seconde est pr\u00e9cieuse.Choisissez la recette : Choisissez la recette \u00e0 pr\u00e9parer. Plus une recette est compliqu\u00e9e, plus elle rapporte de points.Cuisinez en \u00e9quipe : Chaque cuistot g\u00e8re une partie des cartes ingr\u00e9dients et ustensiles de sa brigade. Coordonnez-vous pour r\u00e9ussir les recettes en empilant les cartes sur le plateau de cuisson. Attention au sablier !Servez vos clients : Respectez les demandes de vos clients. Servez-leur les meilleures recettes pour marquer un maximum de points.Mettez la pression \u00e0 vos concurrents : Gr\u00e2ce \u00e0 l\u2019utilisation astucieuse du sablier, plus une \u00e9quipe est rapide, moins elle laisse de temps \u00e0 ses adversaires. Pr\u00e9parez des recettes rapides pour pousser vos adversaires \u00e0 la faute ! Servez tous vos clients les premiers pour leur imposer des malus.Pimentez le jeu : Jouez en version expert avec les r\u00e8gles additionnelles :Faites des combos en servant plusieurs clients \u00e0 la foisLancez des d\u00e9fis cocasses \u00e0 vos adversaires pour les pousser \u00e0 la fauteGagnez des pouvoirs sp\u00e9ciaux gr\u00e2ce aux cartes chefs cuistots (\u00e0 d\u00e9bloquer)\n", "little_description": "Cuistot Fury est un jeu de comp\u00e9tition en \u00e9quipes dans lequel les joueurs rejoignent une brigade de cuistots et d\u00e9fient leurs concurrents dans des duels gastronomiques \u00e0 couteaux tir\u00e9s.", "url_image": "https://cdn1.philibertnet.com/463777-large_default/cuistot-fury.jpg", "prix": "19,50 \u20ac", "Theme": "\nAlimentation ", "mecanique": "\n\u00c9quipe,\u00a0Temps r\u00e9el ", "Auteur": "\nMathieu Baiget "}