{"url": "https://www.philibertnet.com/fr/oya/46627-pas-de-bras-gold-edition-3760207030015.html#img", "name": "Pas de Bras - Gold Edition", "minage": "\n\u00e0 partir de 9 ans\n", "duree": "\nmoins de 30mn\n", "nb_joueur": "\n\n3 \u00e0 6 joueur(s)\n\n", "description": "\nAmassez les chocolats, doublez la dose de cacao, mais \u00e9vitez l'huile de palme qui g\u00e2terait tout. Et surtout, souvenez vous : Pas de bras... pas de chocolat ! Ce jeu, o\u00f9 il faut savoir offrir des cadeaux \u00e0 ses ennemis, vous fera autant rire que r\u00e9fl\u00e9chir.Contient : 60 cartes,1 marqueur Oya,une r\u00e8gle du jeu.\n", "little_description": "Pas de Bras Gold Edition est un petit jeu de cartes malin qui s'explique facilement pour des parties rapides. Amassez les chocolats, doublez la dose de cacao, mais \u00e9vitez l'huile de palme qui g\u00e2terait tout.", "url_image": "https://cdn1.philibertnet.com/362944-large_default/pas-de-bras-gold-edition.jpg", "prix": "14,50 \u20ac", "Theme": "\nAlimentation ", "mecanique": "\nCombinaison,\u00a0Cartes ", "Auteur": "\nHorst-Rainer R\u00f6sner "}